pymeistertask/__init__.py
pymeistertask/api.py
pymeistertask/comments.py
pymeistertask/labels.py
pymeistertask/persons.py
pymeistertask/projects.py
pymeistertask/resource.py
pymeistertask/sections.py
pymeistertask/tasklabels.py
pymeistertask/tasks.py
pymeistertask-0.1.2.dist-info/LICENSE
pymeistertask-0.1.2.dist-info/METADATA
pymeistertask-0.1.2.dist-info/WHEEL
pymeistertask-0.1.2.dist-info/top_level.txt
pymeistertask-0.1.2.dist-info/RECORD
