Metadata-Version: 2.1
Name: pymeistertask
Version: 0.1.2
Summary: MeisterTask client library
Home-page: https://github.com/tomkins/pymeistertask
Maintainer: Alex Tomkins
Maintainer-email: tomkins@darkzone.net
License: BSD
Platform: any
Classifier: Intended Audience :: Developers
Classifier: License :: OSI Approved :: BSD License
Classifier: Operating System :: OS Independent
Classifier: Programming Language :: Python
Classifier: Programming Language :: Python :: 3
Classifier: Programming Language :: Python :: 3.4
Classifier: Programming Language :: Python :: 3.5
Classifier: Programming Language :: Python :: 3.6
Classifier: Programming Language :: Python :: 3.7
Requires-Python: >=3.4
Requires-Dist: requests (>=2.0.0)
